{"id":24159,"email":"jdebidin@student.42.fr","login":"jdebidin","first_name":"Jaskaran","last_name":"Debidin","url":"https://api.intra.42.fr/v2/users/jdebidin","phone":null,"displayname":"Jaskaran Debidin","image_url":"https://cdn.intra.42.fr/users/jdebidin.jpg","staff?":false,"correction_point":3,"pool_month":"february","pool_year":"2017","location":null,"wallet":0,"groups":[],"cursus_users":[{"grade":null,"level":0.0,"skills":[],"id":17701,"begin_at":"2017-02-11T18:42:00.000Z","end_at":"2017-03-11T18:42:00.000Z","cursus_id":11,"user":{"id":24159,"login":"jdebidin","url":"https://api.intra.42.fr/v2/users/jdebidin"},"cursus":{"id":11,"created_at":"2015-12-08T11:59:17.803Z","name":"BootCamp","slug":"bootcamp"}}],"projects_users":[{"id":470524,"occurrence":0,"final_mark":null,"status":"waiting_for_correction","validated?":null,"current_team_id":1514180,"project":{"id":626,"name":"Day 10","slug":"bootcamp-day-10","parent_id":null},"cursus_ids":[11]},{"id":470525,"occurrence":0,"final_mark":0,"status":"finished","validated?":false,"current_team_id":1514181,"project":{"id":625,"name":"Day 11","slug":"bootcamp-day-11","parent_id":null},"cursus_ids":[11]},{"id":470852,"occurrence":0,"final_mark":0,"status":"finished","validated?":false,"current_team_id":1514567,"project":{"id":628,"name":"Day 13","slug":"bootcamp-day-13","parent_id":null},"cursus_ids":[11]},{"id":473628,"occurrence":0,"final_mark":9,"status":"finished","validated?":false,"current_team_id":1518293,"project":{"id":681,"name":"Joburg-Final-Exam","slug":"bootcamp-joburg-final-exam","parent_id":null},"cursus_ids":[11]},{"id":466266,"occurrence":0,"final_mark":0,"status":"finished","validated?":false,"current_team_id":1508765,"project":{"id":606,"name":"Day 01","slug":"bootcamp-day-01","parent_id":null},"cursus_ids":[11]},{"id":466342,"occurrence":0,"final_mark":0,"status":"finished","validated?":false,"current_team_id":1508851,"project":{"id":672,"name":"Day 03","slug":"bootcamp-day-03","parent_id":null},"cursus_ids":[11]},{"id":471665,"occurrence":0,"final_mark":0,"status":"finished","validated?":false,"current_team_id":1515894,"project":{"id":631,"name":"BSQ","slug":"bootcamp-bsq","parent_id":null},"cursus_ids":[11]},{"id":471673,"occurrence":0,"final_mark":0,"status":"finished","validated?":false,"current_team_id":1516177,"project":{"id":629,"name":"Colle 02","slug":"bootcamp-colle-02","parent_id":null},"cursus_ids":[11]},{"id":466134,"occurrence":0,"final_mark":0,"status":"finished","validated?":false,"current_team_id":1508633,"project":{"id":670,"name":"Day 00","slug":"bootcamp-day-00","parent_id":null},"cursus_ids":[11]},{"id":467221,"occurrence":0,"final_mark":0,"status":"finished","validated?":false,"current_team_id":1510156,"project":{"id":616,"name":"Day 04","slug":"bootcamp-day-04","parent_id":null},"cursus_ids":[11]},{"id":467222,"occurrence":0,"final_mark":0,"status":"finished","validated?":false,"current_team_id":1510390,"project":{"id":623,"name":"Colle 00","slug":"bootcamp-colle-00","parent_id":null},"cursus_ids":[11]},{"id":471935,"occurrence":0,"final_mark":0,"status":"finished","validated?":false,"current_team_id":1515897,"project":{"id":698,"name":"Joburg-Exam-02","slug":"bootcamp-joburg-exam-02","parent_id":null},"cursus_ids":[11]},{"id":466340,"occurrence":0,"final_mark":0,"status":"finished","validated?":false,"current_team_id":1508849,"project":{"id":608,"name":"Day 02","slug":"bootcamp-day-02","parent_id":null},"cursus_ids":[11]},{"id":467809,"occurrence":0,"final_mark":null,"status":"waiting_for_correction","validated?":null,"current_team_id":1510959,"project":{"id":621,"name":"Day 07","slug":"bootcamp-day-07","parent_id":null},"cursus_ids":[11]},{"id":467808,"occurrence":0,"final_mark":0,"status":"finished","validated?":false,"current_team_id":1510956,"project":{"id":618,"name":"Day 06","slug":"bootcamp-day-06","parent_id":null},"cursus_ids":[11]},{"id":467810,"occurrence":0,"final_mark":0,"status":"finished","validated?":false,"current_team_id":1510960,"project":{"id":620,"name":"Day 08","slug":"bootcamp-day-08","parent_id":null},"cursus_ids":[11]},{"id":470853,"occurrence":0,"final_mark":0,"status":"finished","validated?":false,"current_team_id":1514568,"project":{"id":627,"name":"Day 12","slug":"bootcamp-day-12","parent_id":null},"cursus_ids":[11]},{"id":468179,"occurrence":0,"final_mark":0,"status":"finished","validated?":false,"current_team_id":1511628,"project":{"id":680,"name":"Joburg-Exam-01","slug":"bootcamp-joburg-exam-01","parent_id":null},"cursus_ids":[11]}],"languages_users":[{"id":36519,"language_id":2,"user_id":24159,"position":1,"created_at":"2017-02-09T12:05:51.107Z"}],"achievements":[],"titles":[],"partnerships":[],"patroned":[],"patroning":[],"expertises_users":[],"campus":[{"id":5,"name":"Johannesburg","time_zone":"Africa/Johannesburg","language":{"id":2,"name":"English","identifier":"en","created_at":"2015-04-14T16:07:38.122Z","updated_at":"2017-03-15T12:50:46.419Z"},"users_count":732,"vogsphere_id":1}],"campus_users":[{"id":14075,"user_id":24159,"campus_id":5,"is_primary":true}]}